{"data":{"content":[{"key":"kinhkinhtuan10","attrs":{"pathname":"/trang-chu/kinh/kinh-tuan-1","hash":""},"type":"contentBlock","content":[{"key":"kinhkinhtuan10p0","type":"paragraph","content":[{"type":"text","text":"\tVườn Lạn Uyển sanh hoa đã héo.\n\tKhối hình hài đã chịu rã tan;\n\t\tBảy dây oan nghiệt hết ràng,\nBợn trần rửa sạch muôn ngàn đau thương.\n\tKìa Thiên cảnh con đường vòi vọi.\n\tÁnh Hồng Quân đương chói Ngọc Lầu;\n\t\tCung Thiềm gắng bước cho mau.\nThoát ba Thần phẩm đứng đầu Tam Thiên.\n\tKhá tỉnh thức tiền duyên nhớ lại,\n\tÐoạn cho rồi oan trái buổi sanh;\n\t\tÐem mình nương bóng Chí Linh,\nÐịnh tâm chí Thánh mới gìn ngôi xưa.\n\tHồn định tỉnh đã vừa định tỉnh.\n\tPhách anh linh ắt phải anh linh;\n\t\tQuản bao Thập ác Lục hình,\nGiải thi thoát khổ diệt hình đoạt căn.\n"},{"type":"text","text":"NAM MÔ CAO ĐÀI TIÊN ÔNG ĐẠI BỒ TÁT MA HA TÁT","attrs":{"fontWeight":"bold"}},{"type":"text","text":"\n"}]}],"focused":false}],"name":"KINH ĐỆ NHỨT CỬU","key":"kinh-tuan-1","type":"block","event":"quan-hon-tang-te"}}
